Metadata-Version: 2.4
Name: iflow-mcp-intbjw-fofa-mcp-server
Version: 0.1.0
Summary: A server for querying FOFA API using MCP
Requires-Python: >=3.11
Requires-Dist: httpx>=0.28.1
Requires-Dist: mcp[cli]>=1.4.0
